divide/__init__.py
divide/divide_by_three.py
multiply/__init__.py
multiply/multiply_by_three.py
basictest-0.0.1.dist-info/LICENSE
basictest-0.0.1.dist-info/METADATA
basictest-0.0.1.dist-info/WHEEL
basictest-0.0.1.dist-info/top_level.txt
basictest-0.0.1.dist-info/RECORD
