Metadata-Version: 2.1
Name: basictest
Version: 0.0.1
Summary: A test Python Package
Home-page: https://github.com/agnivomallick/basictest
Author: Agnivo Mallick
Author-email: agnivomallick@gmail.com
Project-URL: Bug Tracker, https://github.com/agnivomallick/basictest/issues
Project-URL: repository, https://github.com/agnivomallick/basictest
Classifier: Programming Language :: Python :: 3
Classifier: License :: OSI Approved :: MIT License
Classifier: Operating System :: OS Independent
Requires-Python: >=3.9
License-File: LICENSE
